LICENSE.txt
MANIFEST.in
README.rst
pyproject.toml
setup.py
tutor_jupyter.egg-info/PKG-INFO
tutor_jupyter.egg-info/SOURCES.txt
tutor_jupyter.egg-info/dependency_links.txt
tutor_jupyter.egg-info/entry_points.txt
tutor_jupyter.egg-info/requires.txt
tutor_jupyter.egg-info/top_level.txt
tutorjupyter/__about__.py
tutorjupyter/__init__.py
tutorjupyter/plugin.py
tutorjupyter/patches/.gitignore
tutorjupyter/patches/caddyfile
tutorjupyter/patches/k8s-deployments
tutorjupyter/patches/k8s-jobs
tutorjupyter/patches/k8s-services
tutorjupyter/patches/kustomization-configmapgenerator
tutorjupyter/patches/local-docker-compose-dev-services
tutorjupyter/patches/local-docker-compose-jobs-services
tutorjupyter/patches/local-docker-compose-services
tutorjupyter/patches/openedx-common-settings
tutorjupyter/patches/openedx-development-settings
tutorjupyter/patches/openedx-dockerfile-post-python-requirements
tutorjupyter/templates/jupyter/apps/.gitignore
tutorjupyter/templates/jupyter/apps/jupyterhub_config.py
tutorjupyter/templates/jupyter/build/.gitignore
tutorjupyter/templates/jupyter/build/hub/Dockerfile
tutorjupyter/templates/jupyter/build/lab/Dockerfile
tutorjupyter/templates/jupyter/build/lab/config.py
tutorjupyter/templates/jupyter/tasks/jupyterhub/init
tutorjupyter/templates/jupyter/tasks/mysql/init