Metadata-Version: 2.1
Name: tutor-jupyter
Version: 18.1.1
Summary: Jupyter Notebook plugin for Tutor
Home-page: https://github.com/overhangio/tutor-jupyter
Author: Edly
Maintainer: Edly
Maintainer-email: abdul.muqadim@arbisoft.com
License: AGPLv3
Project-URL: Code, https://github.com/overhangio/tutor-jupyter
Project-URL: Issue tracker, https://github.com/overhangio/tutor-jupyter/issues
Classifier: Development Status :: 5 - Production/Stable
Classifier: Intended Audience :: Developers
Classifier: License :: OSI Approved :: GNU Affero General Public License v3
Classifier: Operating System :: OS Independent
Classifier: Programming Language :: Python
Classifier: Programming Language :: Python :: 3.9
Classifier: Programming Language :: Python :: 3.10
Classifier: Programming Language :: Python :: 3.11
Classifier: Programming Language :: Python :: 3.12
Requires-Python: >=3.9
License-File: LICENSE.txt
Requires-Dist: tutor<19.0.0,>=18.0.0
Requires-Dist: tutor-mfe<19.0.0,>=18.0.0
Provides-Extra: dev
Requires-Dist: tutor[dev]<19.0.0,>=18.0.0; extra == "dev"
